{
  "version": "2.0.0",
  "system": "Karzalay Design System",
  "lastUpdated": "2026-05-17",
  "global": {
    "spacing": {
      "scale-4": "4px", "scale-8": "8px", "scale-12": "12px", "scale-16": "16px",
      "scale-24": "24px", "scale-32": "32px", "scale-48": "48px", "scale-64": "64px"
    },
    "semantics": { "error": "#EF4444", "success": "#10B981", "warning": "#F59E0B" }
  },
  "themes": {
    "google-minimalist": {
      "name": "Google Minimalist",
      "palette": {
        "primary": "#2B4CFF", "secondary": "#475569", "background": "#F8F9FA", "surface": "#FFFFFF", "border": "#E2E8F0"
      }
    },
    "dev-precision": {
      "name": "Dev Precision",
      "palette": {
        "primary": "#0D9488", "secondary": "#6366F1", "background": "#FAFAFA", "surface": "#FFFFFF", "border": "#E5E7EB"
      }
    },
    "warm-organic": {
      "name": "Warm Organic",
      "palette": {
        "primary": "#0F766E", "secondary": "#D97706", "background": "#FCFBF7", "surface": "rgba(255,255,255,0.7)", "border": "rgba(0,0,0,0.05)"
      }
    },
    "cyber-stripe": {
      "name": "Cyber Stripe",
      "palette": {
        "primary": "#4F46E5", "secondary": "#06B6D4", "background": "#F3F4F6", "surface": "#FFFFFF", "border": "#D1D5DB"
      }
    },
    "nordic-functionalist": {
      "name": "Nordic Minimal",
      "palette": {
        "primary": "#059669", "secondary": "#71717A", "background": "#F4F4F5", "surface": "#FFFFFF", "border": "#E4E4E7"
      }
    },
    "academic-renaissance": {
      "name": "Academic Notion",
      "palette": {
        "primary": "#991B1B", "secondary": "#1E3A8A", "background": "#FCFCFA", "surface": "#FFFFFF", "border": "#E5E7EB"
      }
    },
    "high-fashion-swiss": {
      "name": "Fashion Swiss",
      "palette": {
        "primary": "#2B4CFF", "secondary": "#18181B", "background": "#FAFAFA", "surface": "#FFFFFF", "border": "#D4D4D8"
      }
    },
    "neo-renaissance-gold": {
      "name": "Luxury Gold",
      "palette": {
        "primary": "#B45309", "secondary": "#DB2777", "background": "#FAF9F5", "surface": "#FFFFFF", "border": "#EAE7E1"
      }
    },
    "cyber-glow": {
      "name": "Web3 Glow",
      "palette": {
        "primary": "#8B5CF6", "secondary": "#10B981", "background": "#F8FAFC", "surface": "#FFFFFF", "border": "#E2E8F0"
      }
    },
    "aero-grid": {
      "name": "Aero Designer",
      "palette": {
        "primary": "#3B82F6", "secondary": "#4B5563", "background": "#F8FAFC", "surface": "#FFFFFF", "border": "#E2E8F0"
      }
    },
    "academic-purple-amethyst": {
      "name": "Academic Amethyst",
      "palette": {
        "primary": "#7C3AED", "secondary": "#D946EF", "background": "#FAF8FC", "surface": "#FFFFFF", "border": "#EAE5F3"
      }
    },
    "academic-purple-indigo": {
      "name": "Academic Indigo",
      "palette": {
        "primary": "#4F46E5", "secondary": "#8B5CF6", "background": "#FCFBFE", "surface": "#FFFFFF", "border": "#E8E7EC"
      }
    },
    "academic-purple-sunset": {
      "name": "Academic Sunset",
      "palette": {
        "primary": "#6D28D9", "secondary": "#EC4899", "background": "#FAF7F2", "surface": "#FFFFFF", "border": "#EDE4E2"
      }
    }
  }
}
